<?xml version="1.0"?>
<QuestsDefinitions
     level="slums_cl_tunnel"
     pxsl_line="3">
    <Quest
         name="Slums_Cleansing_Tunnel"
         parent="Zone_Slums_Cleansing_Tunnel"
         leading_portal="portal_exit_slums_cleansing_09_tunnel"
         glued="true"
         pxsl_line="5">
        <Phase
             type="AND"
             name="_"
             objective="&amp;ChallengeDZObj_Explore&amp;"
             pxsl_line="6">
            <Path
                 pxsl_line="6">
                <Phase
                     type="go to"
                     name="Slums_Cleansing_09_Tunnel - Start "
                     distance="0"
                     show_locations="true"
                     pxsl_line="7">
                    <Destination
                         pxsl_line="7">
                        <QuestObject
                             class="SensorGoTo"
                             name="Tunnel_DeadZone_Marker_2"
                             pxsl_line="7" />
                    </Destination>
                    <DebugPlayerPosition
                         pxsl_line="8">
                        <QuestObject
                             class="SpawnPoint"
                             name="sp_slums_interior_cleansing_09"
                             pxsl_line="8" />
                    </DebugPlayerPosition>
                </Phase>
                <Phase
                     type="enable"
                     name="_"
                     pxsl_line="9">
                    <Object
                         pxsl_line="10">
                        <QuestObject
                             class="SpawnPoint"
                             name="Tunnel_Hole_SafeZone_Sp"
                             pxsl_line="10" />
                    </Object>
                </Phase>
                <Phase
                     type="checkpoint"
                     name="_"
                     pxsl_line="11">
                    <Destination
                         pxsl_line="11">
                        <QuestObject
                             class="SpawnPoint"
                             name="sp_slums_interior_cleansing_09"
                             pxsl_line="11" />
                    </Destination>
                </Phase>
                <Phase
                     type="AND"
                     name="_"
                     pxsl_line="12">
                    <Path
                         pxsl_line="13">
                        <!-- -obj=&ChallengeDZObj_SearchForSupplies&      -->
                        <Phase
                             type="AND"
                             name="_"
                             pxsl_line="14">
                            <Path
                                 pxsl_line="15">
                                <Phase
                                     type="take item"
                                     name="_"
                                     show_locations="false"
                                     pxsl_line="16">
                                    <Item
                                         pxsl_line="16">
                                        <QuestObject
                                             class="QuestLootableItem"
                                             name="Wagon_Loot_1"
                                             pxsl_line="16" />
                                    </Item>
                                    <SpecificLocation
                                         pxsl_line="17">
                                        <QuestObject
                                             class="ZoneBox"
                                             name="Tunnel_ZoneBox_Loot_1"
                                             pxsl_line="17" />
                                    </SpecificLocation>
                                </Phase>
                            </Path>
                            <Path
                                 pxsl_line="18">
                                <Phase
                                     type="take item"
                                     name="_"
                                     show_locations="false"
                                     pxsl_line="19">
                                    <Item
                                         pxsl_line="19">
                                        <QuestObject
                                             class="QuestLootableItem"
                                             name="Wagon_Loot_2"
                                             pxsl_line="19" />
                                    </Item>
                                    <SpecificLocation
                                         pxsl_line="20">
                                        <QuestObject
                                             class="ZoneBox"
                                             name="Tunnel_ZoneBox_Loot_2"
                                             pxsl_line="20" />
                                    </SpecificLocation>
                                </Phase>
                            </Path>
                            <Path
                                 pxsl_line="21">
                                <Phase
                                     type="take item"
                                     name="_"
                                     show_locations="false"
                                     pxsl_line="22">
                                    <Item
                                         pxsl_line="22">
                                        <QuestObject
                                             class="QuestLootableItem"
                                             name="Wagon_Loot_3"
                                             pxsl_line="22" />
                                    </Item>
                                    <SpecificLocation
                                         pxsl_line="23">
                                        <QuestObject
                                             class="ZoneBox"
                                             name="Tunnel_ZoneBox_Loot_3"
                                             pxsl_line="23" />
                                    </SpecificLocation>
                                </Phase>
                            </Path>
                            <Path
                                 pxsl_line="24">
                                <Phase
                                     type="take item"
                                     name="_"
                                     show_locations="false"
                                     pxsl_line="25">
                                    <Item
                                         pxsl_line="25">
                                        <QuestObject
                                             class="QuestLootableItem"
                                             name="Wagon_Loot_4"
                                             pxsl_line="25" />
                                    </Item>
                                    <SpecificLocation
                                         pxsl_line="26">
                                        <QuestObject
                                             class="ZoneBox"
                                             name="Tunnel_ZoneBox_Loot_4"
                                             pxsl_line="26" />
                                    </SpecificLocation>
                                </Phase>
                            </Path>
                            <Path
                                 pxsl_line="27">
                                <Phase
                                     type="take item"
                                     name="_"
                                     show_locations="false"
                                     pxsl_line="28">
                                    <Item
                                         pxsl_line="28">
                                        <QuestObject
                                             class="QuestLootableItem"
                                             name="Wagon_Loot_5"
                                             pxsl_line="28" />
                                    </Item>
                                    <SpecificLocation
                                         pxsl_line="29">
                                        <QuestObject
                                             class="ZoneBox"
                                             name="Tunnel_ZoneBox_Loot_5"
                                             pxsl_line="29" />
                                    </SpecificLocation>
                                </Phase>
                            </Path>
                        </Phase>
                    </Path>
                    <Path
                         pxsl_line="30">
                        <Phase
                             type="wait guard"
                             name="_"
                             time="10"
                             pxsl_line="31" />
                        <Phase
                             type="enable"
                             name="_"
                             pxsl_line="32">
                            <Object
                                 pxsl_line="32">
                                <QuestObject
                                     class="SensorAmbientMusicArea"
                                     name="Railway_Tunnel_Music"
                                     pxsl_line="32" />
                            </Object>
                        </Phase>
                    </Path>
                </Phase>
                <Phase
                     type="enable"
                     name="_"
                     state="disabled"
                     pxsl_line="33">
                    <Object
                         pxsl_line="33">
                        <QuestObject
                             class="IntensityArea"
                             name="Tunnel_Intensity_High"
                             pxsl_line="33" />
                    </Object>
                </Phase>
                <Phase
                     type="enable"
                     name="_"
                     pxsl_line="34">
                    <Object
                         pxsl_line="35">
                        <QuestObject
                             class="IntensityArea"
                             name="Tunnel_Intensity_Low"
                             pxsl_line="35" />
                    </Object>
                    <Object
                         pxsl_line="36">
                        <QuestObject
                             class="SpawnBlocker"
                             name="Tunnel_SpawnBlocker_2"
                             pxsl_line="36" />
                    </Object>
                </Phase>
                <Phase
                     type="enable"
                     name="_"
                     state="disabled"
                     pxsl_line="37">
                    <Object
                         pxsl_line="38">
                        <QuestObject
                             class="SensorAmbientSoundArea"
                             name="SASA_Tunnel_Additional"
                             pxsl_line="38" />
                    </Object>
                    <Object
                         pxsl_line="39">
                        <QuestObject
                             class="SensorAmbientMusicArea"
                             name="Railway_Tunnel_Music"
                             pxsl_line="39" />
                    </Object>
                </Phase>
                <Phase
                     type="checkpoint"
                     name="Slums_Cleansing_09_Tunnel - End "
                     pxsl_line="40">
                    <Destination
                         pxsl_line="40">
                        <QuestObject
                             class="SpawnPoint"
                             name="sp_slums_interior_cleansing_09"
                             pxsl_line="40" />
                    </Destination>
                    <DebugPlayerPosition
                         pxsl_line="41">
                        <QuestObject
                             class="SpawnPoint"
                             name="sp_slums_interior_cleansing_09"
                             pxsl_line="41" />
                    </DebugPlayerPosition>
                </Phase>
            </Path>
        </Phase>
    </Quest>
    <Quest
         name="__Slums_Cleansing_Kill"
         parent="Zone_Slums_Cleansing_Tunnel"
         pxsl_line="43">
        <Phase
             type="go to"
             name="_"
             distance="0"
             show_locations="false"
             pxsl_line="44">
            <Destination
                 pxsl_line="44">
                <QuestObject
                     class="SensorGoTo"
                     name="Tunnel_DeadZone_Marker_2"
                     pxsl_line="44" />
            </Destination>
        </Phase>
        <Phase
             type="AND"
             name="_"
             pxsl_line="45">
            <Path
                 pxsl_line="46">
                <Phase
                     type="kill"
                     name="_"
                     show_locations="false"
                     pxsl_line="47">
                    <Spawner
                         pxsl_line="47">
                        <QuestObject
                             class="AISpawnBoxNumber"
                             name="Railway_Zombies_1"
                             pxsl_line="47" />
                    </Spawner>
                </Phase>
                <Phase
                     type="enable"
                     name="_"
                     state="disabled"
                     pxsl_line="48">
                    <Object
                         pxsl_line="48">
                        <QuestObject
                             class="AISpawnBoxNumber"
                             name="Railway_Zombies_1"
                             pxsl_line="48" />
                    </Object>
                </Phase>
            </Path>
            <Path
                 pxsl_line="49">
                <Phase
                     type="kill"
                     name="_"
                     show_locations="false"
                     pxsl_line="50">
                    <Spawner
                         pxsl_line="50">
                        <QuestObject
                             class="AISpawnBoxNumber"
                             name="Railway_Zombies_2"
                             pxsl_line="50" />
                    </Spawner>
                </Phase>
                <Phase
                     type="enable"
                     name="_"
                     state="disabled"
                     pxsl_line="51">
                    <Object
                         pxsl_line="51">
                        <QuestObject
                             class="AISpawnBoxNumber"
                             name="Railway_Zombies_2"
                             pxsl_line="51" />
                    </Object>
                </Phase>
            </Path>
            <Path
                 pxsl_line="52">
                <Phase
                     type="kill"
                     name="_"
                     show_locations="false"
                     pxsl_line="53">
                    <Spawner
                         pxsl_line="53">
                        <QuestObject
                             class="AISpawnBoxNumber"
                             name="Railway_Zombies_3"
                             pxsl_line="53" />
                    </Spawner>
                </Phase>
                <Phase
                     type="enable"
                     name="_"
                     state="disabled"
                     pxsl_line="54">
                    <Object
                         pxsl_line="54">
                        <QuestObject
                             class="AISpawnBoxNumber"
                             name="Railway_Zombies_3"
                             pxsl_line="54" />
                    </Object>
                </Phase>
            </Path>
        </Phase>
        <Phase
             type="checkpoint"
             name="_"
             pxsl_line="55">
            <Destination
                 pxsl_line="55">
                <QuestObject
                     class="SpawnPoint"
                     name="sp_slums_interior_cleansing_09"
                     pxsl_line="55" />
            </Destination>
        </Phase>
    </Quest>
    <Quest
         name="__Slums_Cleansing_Tunnel_Pipe_1"
         parent="Zone_Slums_Cleansing_Tunnel"
         pxsl_line="59">
        <Phase
             type="go to"
             name=" Rolling_Pipe_1 "
             distance="0"
             show_locations="false"
             pxsl_line="60">
            <Destination
                 pxsl_line="60">
                <QuestObject
                     class="SensorGoTo"
                     name="Tunnel_DeadZone_Marker_2"
                     pxsl_line="60" />
            </Destination>
            <DebugPlayerPosition
                 pxsl_line="61">
                <QuestObject
                     class="SpawnPoint"
                     name="sp_slums_interior_cleansing_09"
                     pxsl_line="61" />
            </DebugPlayerPosition>
        </Phase>
        <Phase
             type="use"
             name="_"
             desired_state="on"
             show_locations="false"
             pxsl_line="62">
            <Trigger
                 pxsl_line="62">
                <QuestObject
                     class="PhysicalSwitchDI"
                     name="Push_Pipe_1"
                     pxsl_line="62" />
            </Trigger>
        </Phase>
        <Phase
             type="set skin"
             name="_"
             skin_name="Default"
             pxsl_line="63">
            <ModelObject
                 pxsl_line="63">
                <QuestObject
                     class="PhysicalSwitchDI"
                     name="Push_Pipe_1"
                     pxsl_line="63" />
            </ModelObject>
        </Phase>
        <Phase
             type="AND"
             name="_"
             pxsl_line="64">
            <Path
                 pxsl_line="65">
                <Phase
                     type="movie"
                     name="_"
                     movie="Movie_Rolling_Pipe_01"
                     pxsl_line="66" />
            </Path>
            <Path
                 pxsl_line="67">
                <Phase
                     type="wait guard"
                     name="_"
                     time="5.5"
                     pxsl_line="68" />
                <Phase
                     type="enable"
                     name="_"
                     pxsl_line="69">
                    <Object
                         pxsl_line="70">
                        <QuestObject
                             class="AllLethalObject"
                             name="Rolling_Pipe_DamageBox_1"
                             pxsl_line="70" />
                    </Object>
                </Phase>
                <Phase
                     type="wait guard"
                     name="_"
                     time="8"
                     pxsl_line="71" />
                <Phase
                     type="enable"
                     name="_"
                     state="disabled"
                     pxsl_line="72">
                    <Object
                         pxsl_line="73">
                        <QuestObject
                             class="AllLethalObject"
                             name="Rolling_Pipe_DamageBox_1"
                             pxsl_line="73" />
                    </Object>
                    <Object
                         pxsl_line="74">
                        <QuestObject
                             class="BoxObjectEnabler"
                             name="switch_enabler"
                             pxsl_line="74" />
                    </Object>
                </Phase>
            </Path>
        </Phase>
        <Phase
             type="checkpoint"
             name="_"
             pxsl_line="75">
            <Destination
                 pxsl_line="75">
                <QuestObject
                     class="SpawnPoint"
                     name="sp_slums_interior_cleansing_09"
                     pxsl_line="75" />
            </Destination>
        </Phase>
    </Quest>
    <Quest
         name="__Slums_Cleansing_Tunnel_Pipe_2"
         parent="Zone_Slums_Cleansing_Tunnel"
         pxsl_line="77">
        <Phase
             type="go to"
             name=" Rolling_Pipe_2 "
             distance="0"
             show_locations="false"
             pxsl_line="78">
            <Destination
                 pxsl_line="78">
                <QuestObject
                     class="SensorGoTo"
                     name="Tunnel_DeadZone_Marker_2"
                     pxsl_line="78" />
            </Destination>
            <DebugPlayerPosition
                 pxsl_line="79">
                <QuestObject
                     class="SpawnPoint"
                     name="sp_slums_interior_cleansing_09"
                     pxsl_line="79" />
            </DebugPlayerPosition>
        </Phase>
        <Phase
             type="use"
             name="_"
             desired_state="on"
             show_locations="false"
             pxsl_line="80">
            <Trigger
                 pxsl_line="80">
                <QuestObject
                     class="PhysicalSwitchDI"
                     name="Push_Pipe_2"
                     pxsl_line="80" />
            </Trigger>
        </Phase>
        <Phase
             type="set skin"
             name="_"
             skin_name="Default"
             pxsl_line="81">
            <ModelObject
                 pxsl_line="81">
                <QuestObject
                     class="PhysicalSwitchDI"
                     name="Push_Pipe_2"
                     pxsl_line="81" />
            </ModelObject>
        </Phase>
        <Phase
             type="AND"
             name="_"
             pxsl_line="82">
            <Path
                 pxsl_line="83">
                <Phase
                     type="movie"
                     name="_"
                     movie="Movie_Rolling_Pipe_2"
                     pxsl_line="84" />
            </Path>
            <Path
                 pxsl_line="85">
                <Phase
                     type="wait guard"
                     name="_"
                     time="5.5"
                     pxsl_line="86" />
                <Phase
                     type="enable"
                     name="_"
                     pxsl_line="87">
                    <Object
                         pxsl_line="88">
                        <QuestObject
                             class="AllLethalObject"
                             name="Rolling_Pipe_DamageBox_2"
                             pxsl_line="88" />
                    </Object>
                </Phase>
                <Phase
                     type="wait guard"
                     name="_"
                     time="8"
                     pxsl_line="89" />
                <Phase
                     type="enable"
                     name="_"
                     state="disabled"
                     pxsl_line="90">
                    <Object
                         pxsl_line="91">
                        <QuestObject
                             class="AllLethalObject"
                             name="Rolling_Pipe_DamageBox_2"
                             pxsl_line="91" />
                    </Object>
                    <Object
                         pxsl_line="92">
                        <QuestObject
                             class="BoxObjectEnabler"
                             name="switch_enabler_02"
                             pxsl_line="92" />
                    </Object>
                </Phase>
            </Path>
        </Phase>
        <Phase
             type="checkpoint"
             name="_"
             pxsl_line="93">
            <Destination
                 pxsl_line="93">
                <QuestObject
                     class="SpawnPoint"
                     name="sp_slums_interior_cleansing_09"
                     pxsl_line="93" />
            </Destination>
        </Phase>
    </Quest>
    <Quest
         name="__Slums_Cleansing_Tunnel_Electric"
         parent="Zone_Slums_Cleansing_Tunnel"
         pxsl_line="95">
        <Phase
             type="go to"
             name=" Rolling_Pipe_3 "
             distance="0"
             show_locations="false"
             pxsl_line="96">
            <Destination
                 pxsl_line="96">
                <QuestObject
                     class="SensorGoTo"
                     name="Tunnel_DeadZone_Marker_2"
                     pxsl_line="96" />
            </Destination>
        </Phase>
        <Phase
             type="enable"
             name="_"
             pxsl_line="97">
            <Object
                 pxsl_line="97">
                <QuestObject
                     class="BlackoutArea"
                     name="Tunnel_BlackOut"
                     pxsl_line="97" />
            </Object>
        </Phase>
        <Phase
             type="use"
             name="_"
             desired_state="on"
             show_locations="false"
             pxsl_line="98">
            <Trigger
                 pxsl_line="98">
                <QuestObject
                     class="PhysicalSwitchDI"
                     name="Tunnel_Electric_Cover"
                     pxsl_line="98" />
            </Trigger>
        </Phase>
        <Phase
             type="use"
             name="_"
             desired_state="on"
             show_locations="false"
             pxsl_line="99">
            <Trigger
                 pxsl_line="99">
                <QuestObject
                     class="PhysicalSwitchDI"
                     name="Tunnel_Electric_Panel"
                     pxsl_line="99" />
            </Trigger>
        </Phase>
        <Phase
             type="set skin"
             name="_"
             skin_name="Emissive"
             pxsl_line="100">
            <ModelObject
                 pxsl_line="100">
                <QuestObject
                     class="PhysicalSwitchDI"
                     name="Tunnel_Electric_Panel"
                     pxsl_line="100" />
            </ModelObject>
        </Phase>
        <Phase
             type="enable"
             name="_"
             state="disabled"
             pxsl_line="101">
            <Object
                 pxsl_line="102">
                <QuestObject
                     class="BlackoutArea"
                     name="Tunnel_BlackOut"
                     pxsl_line="102" />
            </Object>
        </Phase>
        <Phase
             type="enable"
             name="_"
             pxsl_line="103">
            <Object
                 pxsl_line="104">
                <QuestObject
                     class="ElectricityEmitterDI"
                     name="electrical_substation_1::Emitter_A"
                     pxsl_line="104" />
            </Object>
            <Object
                 pxsl_line="105">
                <QuestObject
                     class="ElectricityEmitterDI"
                     name="electrical_substation_3::Emitter_A"
                     pxsl_line="105" />
            </Object>
            <Object
                 pxsl_line="106">
                <QuestObject
                     class="ElectricityEmitterDI"
                     name="electrical_substation_4::Emitter_A"
                     pxsl_line="106" />
            </Object>
            <Object
                 pxsl_line="107">
                <QuestObject
                     class="ElectricityEmitterDI"
                     name="electrical_substation_5::Emitter_A"
                     pxsl_line="107" />
            </Object>
            <Object
                 pxsl_line="108">
                <QuestObject
                     class="SoundEmitterSimple"
                     name="electrical_substation_1::Sound_Emitter_A"
                     pxsl_line="108" />
            </Object>
            <Object
                 pxsl_line="109">
                <QuestObject
                     class="SoundEmitterSimple"
                     name="electrical_substation_3::Sound_Emitter_A"
                     pxsl_line="109" />
            </Object>
            <Object
                 pxsl_line="110">
                <QuestObject
                     class="SoundEmitterSimple"
                     name="electrical_substation_4::Sound_Emitter_A"
                     pxsl_line="110" />
            </Object>
            <Object
                 pxsl_line="111">
                <QuestObject
                     class="SoundEmitterSimple"
                     name="electrical_substation_5::Sound_Emitter_A"
                     pxsl_line="111" />
            </Object>
            <Object
                 pxsl_line="112">
                <QuestObject
                     class="ElectricityEmitterDI"
                     name="Tracks_Ellectric_Emitter_1"
                     pxsl_line="112" />
            </Object>
            <Object
                 pxsl_line="113">
                <QuestObject
                     class="ElectricityEmitterDI"
                     name="Tracks_Ellectric_Emitter_2"
                     pxsl_line="113" />
            </Object>
            <Object
                 pxsl_line="114">
                <QuestObject
                     class="ElectricityEmitterDI"
                     name="Tracks_Ellectric_Emitter_3"
                     pxsl_line="114" />
            </Object>
            <Object
                 pxsl_line="115">
                <QuestObject
                     class="BlackoutArea"
                     name="Tunnel_Enlight"
                     pxsl_line="115" />
            </Object>
        </Phase>
        <Phase
             type="checkpoint"
             name="_"
             pxsl_line="116">
            <Destination
                 pxsl_line="116">
                <QuestObject
                     class="SpawnPoint"
                     name="sp_slums_interior_cleansing_09"
                     pxsl_line="116" />
            </Destination>
        </Phase>
    </Quest>
    <Quest
         name="__Slums_Cleansing_Tunnel_Pipe_3"
         parent="Zone_Slums_Cleansing_Tunnel"
         pxsl_line="120">
        <Phase
             type="go to"
             name=" Rolling_Pipe_3 "
             distance="0"
             show_locations="false"
             pxsl_line="121">
            <Destination
                 pxsl_line="121">
                <QuestObject
                     class="SensorGoTo"
                     name="Tunnel_DeadZone_Marker_2"
                     pxsl_line="121" />
            </Destination>
            <DebugPlayerPosition
                 pxsl_line="122">
                <QuestObject
                     class="SpawnPoint"
                     name="sp_slums_interior_cleansing_09"
                     pxsl_line="122" />
            </DebugPlayerPosition>
        </Phase>
        <Phase
             type="use"
             name="_"
             desired_state="on"
             show_locations="false"
             pxsl_line="123">
            <Trigger
                 pxsl_line="123">
                <QuestObject
                     class="PhysicalSwitchDI"
                     name="Pipe_3"
                     pxsl_line="123" />
            </Trigger>
        </Phase>
        <Phase
             type="set skin"
             name="_"
             skin_name="Default"
             pxsl_line="124">
            <ModelObject
                 pxsl_line="124">
                <QuestObject
                     class="PhysicalSwitchDI"
                     name="Pipe_3"
                     pxsl_line="124" />
            </ModelObject>
        </Phase>
        <Phase
             type="AND"
             name="_"
             pxsl_line="125">
            <Path
                 pxsl_line="126">
                <Phase
                     type="movie"
                     name="_"
                     movie="Movie_Rolling_Pipe_3"
                     pxsl_line="127" />
            </Path>
            <Path
                 pxsl_line="128">
                <Phase
                     type="wait guard"
                     name="_"
                     time="5"
                     pxsl_line="129" />
                <Phase
                     type="enable"
                     name="_"
                     pxsl_line="130">
                    <Object
                         pxsl_line="131">
                        <QuestObject
                             class="AllLethalObject"
                             name="Rolling_Pipe_DamageBox_3"
                             pxsl_line="131" />
                    </Object>
                </Phase>
                <Phase
                     type="wait guard"
                     name="_"
                     time="8"
                     pxsl_line="132" />
                <Phase
                     type="enable"
                     name="_"
                     state="disabled"
                     pxsl_line="133">
                    <Object
                         pxsl_line="134">
                        <QuestObject
                             class="AllLethalObject"
                             name="Rolling_Pipe_DamageBox_3"
                             pxsl_line="134" />
                    </Object>
                    <Object
                         pxsl_line="135">
                        <QuestObject
                             class="BoxObjectEnabler"
                             name="switch_enabler_03"
                             pxsl_line="135" />
                    </Object>
                </Phase>
            </Path>
        </Phase>
        <Phase
             type="checkpoint"
             name="_"
             pxsl_line="136">
            <Destination
                 pxsl_line="136">
                <QuestObject
                     class="SpawnPoint"
                     name="sp_slums_interior_cleansing_09"
                     pxsl_line="136" />
            </Destination>
        </Phase>
    </Quest>
</QuestsDefinitions>
