<?xml version="1.0"?>
<QuestsDefinitions
     level="testmap_maciekk"
     pxsl_line="3">
    <Quest
         name="__Q_TestMap_Maciekk_Cadmen"
         parent="game_root"
         difficulty="easy"
         quest_giver="Camden"
         reward_set="Q_TestMap_Maciekk_Cadmen_Reward"
         pxsl_line="5">
        <Phase
             type="go to"
             name="_"
             distance="5"
             show_locations="false"
             pxsl_line="6">
            <Destination
                 pxsl_line="6">
                <QuestObject
                     class="SpawnPoint"
                     name="MapStart"
                     pxsl_line="6" />
            </Destination>
        </Phase>
        <Phase
             type="AND"
             name="_"
             objective="Talk To Camden"
             pxsl_line="7">
            <Path
                 pxsl_line="7">
                <Phase
                     type="talk"
                     name="Q_TestMap_Maciekk_Cadmen - START"
                     speaker="Camden"
                     group="Camden_FindAntio_USE"
                     show_locations="false"
                     following_group="Camden_FindAntio_NEA"
                     pxsl_line="8">
                    <DebugPlayerPosition
                         pxsl_line="9">
                        <QuestObject
                             class="SpawnPoint"
                             name="MapStart"
                             pxsl_line="9" />
                    </DebugPlayerPosition>
                </Phase>
            </Path>
        </Phase>
        <Phase
             type="checkpoint"
             name="_"
             pxsl_line="10">
            <Destination
                 pxsl_line="10">
                <QuestObject
                     class="SpawnPoint"
                     name="MapStart"
                     pxsl_line="10" />
            </Destination>
        </Phase>
        <Phase
             type="AND"
             name="Q_TestMap_Maciekk_Cadmen1 - GOTO"
             objective="GO TO"
             pxsl_line="11">
            <Path
                 pxsl_line="11">
                <Phase
                     type="go to"
                     name="_"
                     distance="5"
                     pxsl_line="12">
                    <Destination
                         pxsl_line="12">
                        <QuestObject
                             class="Marker"
                             name="Fake_Quest_Target_01"
                             pxsl_line="12" />
                    </Destination>
                </Phase>
                <!-- ,debugpos SpawnPoint MapStart -->
            </Path>
        </Phase>
        <Phase
             type="checkpoint"
             name="_"
             pxsl_line="14">
            <Destination
                 pxsl_line="14">
                <QuestObject
                     class="SpawnPoint"
                     name="MapStart"
                     pxsl_line="14" />
            </Destination>
        </Phase>
        <!-- ,BLOCK <<Q_TestMap_Maciekk_Cadmen2 - TAKE REWARD>> -obj=<<Take Reward>> -->
            <!-- ,reward _  -->
            <!-- ,debugpos SpawnPoint MapStart -->
        <Phase
             type="checkpoint"
             name="_"
             pxsl_line="18">
            <Destination
                 pxsl_line="18">
                <QuestObject
                     class="SpawnPoint"
                     name="MapStart"
                     pxsl_line="18" />
            </Destination>
        </Phase>
    </Quest>
    <Quest
         name="__Q_TestMap_Maciekk_Brecken"
         parent="game_root"
         difficulty="medium"
         quest_giver="Brecken"
         reward_set="Q_TestMap_Maciekk_Bracken_Reward"
         pxsl_line="20">
        <Phase
             type="go to"
             name="_"
             distance="5"
             show_locations="false"
             pxsl_line="21">
            <Destination
                 pxsl_line="21">
                <QuestObject
                     class="SpawnPoint"
                     name="MapStart"
                     pxsl_line="21" />
            </Destination>
        </Phase>
        <Phase
             type="AND"
             name="_"
             objective="Talk To Brecken"
             pxsl_line="22">
            <Path
                 pxsl_line="22">
                <Phase
                     type="talk"
                     name="Q_TestMap_Maciekk_Brecken - START"
                     speaker="Brecken"
                     group="Brecken_Ambush_USE"
                     show_locations="false"
                     following_group="Brecken_Ambush_NEA"
                     pxsl_line="23">
                    <DebugPlayerPosition
                         pxsl_line="24">
                        <QuestObject
                             class="SpawnPoint"
                             name="MapStart"
                             pxsl_line="24" />
                    </DebugPlayerPosition>
                </Phase>
            </Path>
        </Phase>
        <Phase
             type="checkpoint"
             name="_"
             pxsl_line="25">
            <Destination
                 pxsl_line="25">
                <QuestObject
                     class="SpawnPoint"
                     name="MapStart"
                     pxsl_line="25" />
            </Destination>
        </Phase>
        <Phase
             type="AND"
             name="Q_TestMap_Maciekk_Brecken1 - GOTO"
             objective="GO TO"
             pxsl_line="26">
            <Path
                 pxsl_line="26">
                <Phase
                     type="go to"
                     name="_"
                     distance="5"
                     pxsl_line="27">
                    <Destination
                         pxsl_line="27">
                        <QuestObject
                             class="Marker"
                             name="Fake_Quest_Target_02"
                             pxsl_line="27" />
                    </Destination>
                </Phase>
                <!-- ,debugpos SpawnPoint MapStart -->
            </Path>
        </Phase>
        <Phase
             type="checkpoint"
             name="_"
             pxsl_line="29">
            <Destination
                 pxsl_line="29">
                <QuestObject
                     class="SpawnPoint"
                     name="MapStart"
                     pxsl_line="29" />
            </Destination>
        </Phase>
        <!-- ,BLOCK <<Q_TestMap_Maciekk_Brecken2 - TAKE REWARD>> -obj=<<Take Reward>> -->
            <!-- ,reward _  -->
            <!-- ,debugpos SpawnPoint MapStart -->
        <Phase
             type="checkpoint"
             name="_"
             pxsl_line="33">
            <Destination
                 pxsl_line="33">
                <QuestObject
                     class="SpawnPoint"
                     name="MapStart"
                     pxsl_line="33" />
            </Destination>
        </Phase>
    </Quest>
    <Quest
         name="__Q_TestMap_Maciekk_Troy"
         parent="game_root"
         difficulty="very_hard"
         quest_giver="Troy"
         reward_set="Q_TestMap_Maciekk_Troy_Reward"
         pxsl_line="35">
        <Phase
             type="go to"
             name="_"
             distance="5"
             show_locations="false"
             pxsl_line="36">
            <Destination
                 pxsl_line="36">
                <QuestObject
                     class="SpawnPoint"
                     name="MapStart"
                     pxsl_line="36" />
            </Destination>
        </Phase>
        <Phase
             type="AND"
             name="_"
             objective="Talk To Troy"
             pxsl_line="37">
            <Path
                 pxsl_line="37">
                <Phase
                     type="talk"
                     name="Q_TestMap_Maciekk_Troy - START"
                     speaker="Troy"
                     group="Troy_Device_USE"
                     show_locations="false"
                     following_group="Troy_Device_NEA"
                     pxsl_line="38">
                    <DebugPlayerPosition
                         pxsl_line="39">
                        <QuestObject
                             class="SpawnPoint"
                             name="MapStart"
                             pxsl_line="39" />
                    </DebugPlayerPosition>
                </Phase>
            </Path>
        </Phase>
        <Phase
             type="checkpoint"
             name="_"
             pxsl_line="40">
            <Destination
                 pxsl_line="40">
                <QuestObject
                     class="SpawnPoint"
                     name="MapStart"
                     pxsl_line="40" />
            </Destination>
        </Phase>
        <Phase
             type="AND"
             name="Q_TestMap_Maciekk_Troy1 - GOTO"
             objective="GO TO"
             pxsl_line="41">
            <Path
                 pxsl_line="41">
                <Phase
                     type="go to"
                     name="_"
                     distance="5"
                     pxsl_line="42">
                    <Destination
                         pxsl_line="42">
                        <QuestObject
                             class="Marker"
                             name="Fake_Quest_Target_03"
                             pxsl_line="42" />
                    </Destination>
                </Phase>
                <!-- ,debugpos SpawnPoint MapStart -->
            </Path>
        </Phase>
        <Phase
             type="checkpoint"
             name="_"
             pxsl_line="44">
            <Destination
                 pxsl_line="44">
                <QuestObject
                     class="SpawnPoint"
                     name="MapStart"
                     pxsl_line="44" />
            </Destination>
        </Phase>
        <!-- ,BLOCK <<Q_TestMap_Maciekk_Troy2 - TAKE REWARD>> -obj=<<Take Reward>> -->
            <!-- ,reward _  -->
            <!-- ,debugpos SpawnPoint MapStart -->
        <Phase
             type="checkpoint"
             name="_"
             pxsl_line="48">
            <Destination
                 pxsl_line="48">
                <QuestObject
                     class="SpawnPoint"
                     name="MapStart"
                     pxsl_line="48" />
            </Destination>
        </Phase>
    </Quest>
</QuestsDefinitions>
